MANIFEST.in
project_task.xml
setup.py
./__init__.py
./__openerp__.py
./project_task.py
i18n/ar.po
i18n/cs.po
i18n/de.po
i18n/es.po
i18n/es_CR.po
i18n/fi.po
i18n/fr.po
i18n/hr.po
i18n/hu.po
i18n/it.po
i18n/ja.po
i18n/lt.po
i18n/mk.po
i18n/mn.po
i18n/nb.po
i18n/nl.po
i18n/pad_project.pot
i18n/pl.po
i18n/pt.po
i18n/pt_BR.po
i18n/ro.po
i18n/ru.po
i18n/sl.po
i18n/sv.po
i18n/tr.po
i18n/zh_CN.po
i18n/zh_TW.po
openerp_pad_project.egg-info/PKG-INFO
openerp_pad_project.egg-info/SOURCES.txt
openerp_pad_project.egg-info/dependency_links.txt
openerp_pad_project.egg-info/requires.txt
openerp_pad_project.egg-info/top_level.txt